interp_embed/__init__.py
interp_embed/dataset_analysis.py
interp_embed/llm/__init__.py
interp_embed/llm/prompts.py
interp_embed/llm/utils.py
interp_embed/saes/__init__.py
interp_embed/saes/api_sae.py
interp_embed/saes/base_sae.py
interp_embed/saes/load_sae.py
interp_embed/saes/local_sae.py
interp_embed/saes/utils.py
interp_embed/utils/__init__.py
interp_embed/utils/data_models.py
interp_embed/utils/helpers.py
interp_embed-0.1.0.dist-info/licenses/LICENSE
interp_embed-0.1.0.dist-info/METADATA
interp_embed-0.1.0.dist-info/WHEEL
interp_embed-0.1.0.dist-info/top_level.txt
interp_embed-0.1.0.dist-info/RECORD
