Metadata-Version: 2.4
Name: interp_embed
Version: 0.1.0
Summary: Toolkit for analyzing unstructured datasets with sparse autoencoders
Author: Nick Jiang
License: MIT
Keywords: sparse-autoencoders,sae,interpretability,machine-learning,dataset-analysis,embeddings
Classifier: Development Status :: 3 - Alpha
Classifier: Intended Audience :: Science/Research
Classifier: License :: OSI Approved :: MIT License
Classifier: Programming Language :: Python :: 3
Classifier: Programming Language :: Python :: 3.10
Classifier: Programming Language :: Python :: 3.11
Classifier: Programming Language :: Python :: 3.12
Classifier: Topic :: Scientific/Engineering :: Artificial Intelligence
Requires-Python: >=3.10
License-File: LICENSE
Requires-Dist: goodfire==0.3.4
Requires-Dist: python-dotenv==1.0.1
Requires-Dist: pandas==2.2.3
Requires-Dist: scikit-learn==1.6.1
Requires-Dist: ipykernel
Requires-Dist: tqdm==4.67.1
Requires-Dist: openai>=1.0.0
Requires-Dist: scipy>=1.10.0
Requires-Dist: numpy>=1.24.0
Requires-Dist: torch>=2.0.0
Requires-Dist: transformers>=4.30.0
Requires-Dist: sae-lens>=3.0.0
Requires-Dist: transformer-lens>=1.0.0
Requires-Dist: huggingface-hub>=0.16.0
Requires-Dist: pydantic>=2.0.0
Dynamic: license-file
Dynamic: requires-python
